Metadata-Version: 2.1
Name: VantagePy
Version: 0.0.1
Summary: API client for Alpha Vantage
Home-page: https://github.com/jkalasas/vantagepy
Author: John Kyle Alas-as
Author-email: alasasjohnkyle@gmail.com
License: MIT
Download-URL: https://github.com/jkalasas/vantagepy/archive/refs/tags/0.0.1.tar.gz
Keywords: api,alphavantage,client
Platform: any
Classifier: Development Status :: 3 - Alpha
Classifier: Intended Audience :: Developers
Classifier: License :: OSI Approved :: MIT License
Classifier: Programming Language :: Python :: 3
License-File: LICENSE.txt
